reporelaypy/__init__.py
reporelaypy/checkout.py
reporelaypy/checkoutroute.py
reporelaypy/hooks.py
reporelaypy/webserver.py
reporelaypy/tests/checkout_unittest.py
reporelaypy/tests/checkoutroute_unittest.py
reporelaypy/tests/hooks_unittest.py
reporelaypy-0.8.5.dist-info/LICENSE
reporelaypy-0.8.5.dist-info/METADATA
reporelaypy-0.8.5.dist-info/WHEEL
reporelaypy-0.8.5.dist-info/top_level.txt
reporelaypy-0.8.5.dist-info/RECORD
